{"assets/images/png/gift_pic.png":["assets/images/png/gift_pic.png"],"assets/images/png/phone_otp.png":["assets/images/png/phone_otp.png"],"assets/images/svg/.DS_Store":["assets/images/svg/.DS_Store"],"assets/images/svg/apple.svg":["assets/images/svg/apple.svg"],"assets/images/svg/back.svg":["assets/images/svg/back.svg"],"assets/images/svg/bell_icon.svg":["assets/images/svg/bell_icon.svg"],"assets/images/svg/drawer_icon.svg":["assets/images/svg/drawer_icon.svg"],"assets/images/svg/english.svg":["assets/images/svg/english.svg"],"assets/images/svg/forward.svg":["assets/images/svg/forward.svg"],"assets/images/svg/gift.svg":["assets/images/svg/gift.svg"],"assets/images/svg/google.svg":["assets/images/svg/google.svg"],"assets/images/svg/iPrep.svg":["assets/images/svg/iPrep.svg"],"assets/images/svg/pause.svg":["assets/images/svg/pause.svg"],"assets/images/svg/phone.svg":["assets/images/svg/phone.svg"],"assets/images/svg/play.svg":["assets/images/svg/play.svg"],"assets/images/svg/settings.svg":["assets/images/svg/settings.svg"],"assets/images/svg/splash.svg":["assets/images/svg/splash.svg"],"assets/images/svg/store.svg":["assets/images/svg/store.svg"],"assets/images/svg/trelling.svg":["assets/images/svg/trelling.svg"],"assets/images/svg/true.svg":["assets/images/svg/true.svg"],"packages/cupertino_icons/assets/CupertinoIcons.ttf":["packages/cupertino_icons/assets/CupertinoIcons.ttf"]}